Metadata-Version: 1.0
Name: fm0300-package
Version: 0.2
Summary: Package Description
Home-page: http://example.com
Author: Stephen Hudson
Author-email: shudson@anl.gov
License: UNKNOWN
Platform: UNKNOWN
